paccmann_predictor/__init__.py
paccmann_predictor/models/__init__.py
paccmann_predictor/models/bimodal_mca.py
paccmann_predictor/models/dense.py
paccmann_predictor/models/knn.py
paccmann_predictor/models/paccmann.py
paccmann_predictor/models/paccmann_v2.py
paccmann_predictor/utils/__init__.py
paccmann_predictor/utils/hyperparams.py
paccmann_predictor/utils/interpret.py
paccmann_predictor/utils/layers.py
paccmann_predictor/utils/loss_functions.py
paccmann_predictor/utils/utils.py
paccmann_predictor-1.0.0.dist-info/LICENSE
paccmann_predictor-1.0.0.dist-info/METADATA
paccmann_predictor-1.0.0.dist-info/WHEEL
paccmann_predictor-1.0.0.dist-info/top_level.txt
paccmann_predictor-1.0.0.dist-info/RECORD
