Metadata-Version: 2.1
Name: paccmann_predictor
Version: 1.0.0
Summary: PyTorch implementation of PaccMann
Home-page: https://github.com/PaccMann/paccmann_predictor
Author: Ali Oskooei, Jannis Born, Matteo Manica, Joris Cadow
Author-email: ali.oskooei@gmail.com, jab@zurich.ibm.com, drugilsberg@gmail.com, joriscadow@gmail.com
License-File: LICENSE
Requires-Dist: numpy
Requires-Dist: scipy
Requires-Dist: torch >=1.0.0
Requires-Dist: pandas
Requires-Dist: tqdm
Requires-Dist: rdkit
Requires-Dist: pytoda >=1.1.5
